{
  "gitSyncId": "6915b9d6a2ab6852a3eeef70_a4b7b425-5e89-4399-aa7b-15a0ea0d419f",
  "id": "Suivi fabrication appareil_ReindexSubByParent",
  "pluginId": "postgres-plugin",
  "pluginType": "DB",
  "unpublishedAction": {
    "actionConfiguration": {
      "body": "-- ReindexSubByParent (v2)\n-- Params: this.params.numero_appareil, this.params.parent_master_id\n\nWITH sibs AS (\n  -- Tous les sous-chapitres du même parent pour l'appareil donné\n  SELECT\n    s.master_id,\n    a.include,\n    COALESCE(a.sub_ord_override, s.default_sub_ord) AS ord\n  FROM public.sommaire s\n  JOIN public.sommaire_appareils a ON a.master_id = s.master_id\n  WHERE a.numero_appareil   = {{ this.params.numero_appareil }}\n    AND s.parent_master_id  = {{ this.params.parent_master_id }}\n),\nrank_all AS (\n  SELECT master_id,\n         ROW_NUMBER() OVER (ORDER BY ord, master_id) AS rn_all\n  FROM sibs\n),\nrank_active AS (\n  SELECT master_id,\n         ROW_NUMBER() OVER (ORDER BY ord, master_id) AS rn_active\n  FROM sibs\n  WHERE include IS TRUE\n),\nmerged AS (\n  SELECT a.master_id,\n         a.include,\n         ra.rn_active,\n         r.rn_all\n  FROM public.sommaire_appareils a\n  JOIN rank_all r        ON r.master_id = a.master_id\n  LEFT JOIN rank_active ra ON ra.master_id = a.master_id\n  WHERE a.numero_appareil = {{ this.params.numero_appareil }}\n)\nUPDATE public.sommaire_appareils AS a\nSET sub_ord_override = CASE\n      WHEN m.include IS TRUE THEN m.rn_active       -- actifs compactés 1..N\n      ELSE 1000 + m.rn_all                          -- exclus rangés \"loin\"\n    END\nFROM merged m\nWHERE a.numero_appareil = {{ this.params.numero_appareil }}\n  AND a.master_id       = m.master_id;\n",
      "encodeParamsToggle": true,
      "paginationType": "NONE",
      "pluginSpecifiedTemplates": [
        {
          "value": true
        }
      ],
      "timeoutInMillisecond": 10000
    },
    "confirmBeforeExecute": false,
    "datasource": {
      "id": "Databook - Neon",
      "isAutoGenerated": false,
      "name": "Databook - Neon",
      "pluginId": "postgres-plugin"
    },
    "dynamicBindingPathList": [
      {
        "key": "body"
      }
    ],
    "name": "ReindexSubByParent",
    "pageId": "Suivi fabrication appareil",
    "runBehaviour": "MANUAL",
    "userSetOnLoad": false
  }
}