{
  "gitSyncId": "6915b9d6a2ab6852a3eeef70_81db5936-6e46-4efa-9dc0-857bd6a0bb78",
  "id": "Administration_QryEverwinWithMapping",
  "pluginId": "postgres-plugin",
  "pluginType": "DB",
  "unpublishedAction": {
    "actionConfiguration": {
      "body": "SELECT\n  eu.everwin_user_id,\n  eu.display_name AS employe,\n  um.slack_user_id,              -- 👈 champ réel pour le Select\n  su.display_name AS slack_display_name,\n  COALESCE(um.is_enabled, false) AS mapping_enabled\nFROM public.everwin_users eu\nLEFT JOIN public.user_mapping um\n  ON um.everwin_user_id = eu.everwin_user_id\nLEFT JOIN public.slack_users su\n  ON su.slack_user_id = um.slack_user_id\nWHERE eu.is_active = true\nORDER BY eu.display_name;\n",
      "encodeParamsToggle": true,
      "paginationType": "NONE",
      "pluginSpecifiedTemplates": [
        {
          "value": true
        }
      ],
      "timeoutInMillisecond": 10000
    },
    "confirmBeforeExecute": false,
    "datasource": {
      "id": "Databook - Neon",
      "isAutoGenerated": false,
      "name": "Databook - Neon",
      "pluginId": "postgres-plugin"
    },
    "dynamicBindingPathList": [],
    "name": "QryEverwinWithMapping",
    "pageId": "Administration",
    "runBehaviour": "AUTOMATIC",
    "userSetOnLoad": false
  }
}