{
  "gitSyncId": "6915b9d6a2ab6852a3eeef70_4825dc84-968b-4ad4-9619-2a0b4c6ef81b",
  "id": "Tableau de bord BE_JS_DashboardFab.getStep",
  "pluginId": "js-plugin",
  "pluginType": "JS",
  "unpublishedAction": {
    "actionConfiguration": {
      "encodeParamsToggle": true,
      "jsArguments": [
        {
          "name": "etapes"
        },
        {
          "name": "groupCode"
        }
      ],
      "paginationType": "NONE",
      "timeoutInMillisecond": 10000
    },
    "collectionId": "Tableau de bord BE_JS_DashboardFab",
    "confirmBeforeExecute": false,
    "datasource": {
      "isAutoGenerated": false,
      "name": "UNUSED_DATASOURCE",
      "pluginId": "js-plugin"
    },
    "dynamicBindingPathList": [
      {
        "key": "body"
      }
    ],
    "fullyQualifiedName": "JS_DashboardFab.getStep",
    "name": "getStep",
    "pageId": "Tableau de bord BE",
    "runBehaviour": "MANUAL",
    "userSetOnLoad": false
  }
}