{
  "gitSyncId": "6915b9d6a2ab6852a3eeef70_a7088ea8-1714-4cc5-8c1a-ac62cab6ba07",
  "id": "Suivi fabrication appareil_TrackerModif.isModified",
  "pluginId": "js-plugin",
  "pluginType": "JS",
  "unpublishedAction": {
    "actionConfiguration": {
      "encodeParamsToggle": true,
      "jsArguments": [],
      "paginationType": "NONE",
      "timeoutInMillisecond": 10000
    },
    "collectionId": "Suivi fabrication appareil_TrackerModif",
    "confirmBeforeExecute": false,
    "datasource": {
      "isAutoGenerated": false,
      "name": "UNUSED_DATASOURCE",
      "pluginId": "js-plugin"
    },
    "dynamicBindingPathList": [
      {
        "key": "body"
      }
    ],
    "fullyQualifiedName": "TrackerModif.isModified",
    "name": "isModified",
    "pageId": "Suivi fabrication appareil",
    "runBehaviour": "MANUAL",
    "userSetOnLoad": false
  }
}