{
  "gitSyncId": "6915b9d6a2ab6852a3eeef70_b65689c1-01d9-463e-9d77-c3dac20ed1f5",
  "id": "Charge atelier_ChargeAtelier.aggregateByWeek",
  "pluginId": "js-plugin",
  "pluginType": "JS",
  "unpublishedAction": {
    "actionConfiguration": {
      "encodeParamsToggle": true,
      "jsArguments": [
        {
          "name": "dailyData"
        }
      ],
      "paginationType": "NONE",
      "timeoutInMillisecond": 10000
    },
    "collectionId": "Charge atelier_ChargeAtelier",
    "confirmBeforeExecute": false,
    "datasource": {
      "isAutoGenerated": false,
      "name": "UNUSED_DATASOURCE",
      "pluginId": "js-plugin"
    },
    "dynamicBindingPathList": [
      {
        "key": "body"
      }
    ],
    "fullyQualifiedName": "ChargeAtelier.aggregateByWeek",
    "name": "aggregateByWeek",
    "pageId": "Charge atelier",
    "runBehaviour": "MANUAL",
    "userSetOnLoad": false
  }
}